{
  "current_ranking": -1,
  "current_rank_id": -1,
  "current_rank_rate": null,
  "ranking_datas": [
    {
      "id": 54089605,
      "code": "492658263",
      "nickname": "ブルージャム海賊団",
      "level": 535,
      "score": 227970,
      "achievement": "期待のルーキー",
      "character_id": 14421,
      "rank": 1
    },
    {
      "id": 54416887,
      "code": "929435862",
      "nickname": "ラスカル",
      "level": 1409,
      "score": 226470,
      "achievement": "<icon=common_font_kaizokudoumeidairansen_0058_10th_anniv_1.png>",
      "character_id": 13903,
      "rank": 2
    },
    {
      "id": 4365558,
      "code": "580766463",
      "nickname": "地味ターズ",
      "level": 316,
      "score": 223380,
      "achievement": "<icon=common_font_world_cruise2023_0025_zoro_kantou.png><icon=common_font_pirate_rumble_grandparty_sp_0081_luffy_sabo_ace.png>",
      "character_id": 10153,
      "rank": 3
    },
    {
      "id": 52160195,
      "code": "044203583",
      "nickname": "インターステラー",
      "level": 657,
      "score": 219817,
      "achievement": "<icon=common_font_grandparty_0098_garling_garp_14512_14513.png>の女",
      "character_id": 13472,
      "rank": 4
    },
    {
      "id": 58609765,
      "code": "983298833",
      "nickname": "蚊取り線香",
      "level": 268,
      "score": 219740,
      "achievement": "期待のルーキー",
      "character_id": 13358,
      "rank": 5
    },
    {
      "id": 56415873,
      "code": "233488285",
      "nickname": "C•D•プリン",
      "level": 1410,
      "score": 219135,
      "achievement": "黒足の花嫁",
      "character_id": 10153,
      "rank": 6
    },
    {
      "id": 44480102,
      "code": "730430226",
      "nickname": "ギン",
      "level": 1503,
      "score": 218560,
      "achievement": "期待のルーキー",
      "character_id": 13852,
      "rank": 7
    },
    {
      "id": 63499887,
      "code": "949809239",
      "nickname": "❦Tinker❦",
      "level": 690,
      "score": 217807,
      "achievement": "炎帝“メラメラの実”",
      "character_id": 13472,
      "rank": 8
    },
    {
      "id": 72809692,
      "code": "539914709",
      "nickname": "麦わらの一味",
      "level": 168,
      "score": 217740,
      "achievement": "夢の古代兵器",
      "character_id": 14420,
      "rank": 9
    },
    {
      "id": 60266927,
      "code": "893255551",
      "nickname": "૭閻王૭",
      "level": 1050,
      "score": 217572,
      "achievement": "<icon=common_font_grandparty_0096_nami_yamato_otama_14301_14422.png><icon=common_font_pirate_rumble_grandparty_0064_robin.png>",
      "character_id": 13701,
      "rank": 10
    },
    {
      "id": 25078443,
      "code": "233679786",
      "nickname": "PPAP",
      "level": 490,
      "score": 216297,
      "achievement": "期待のルーキー",
      "character_id": 14551,
      "rank": 11
    },
    {
      "id": 6843389,
      "code": "496490837",
      "nickname": "JAWS",
      "level": 398,
      "score": 215690,
      "achievement": "Dの一族の未来",
      "character_id": 13472,
      "rank": 12
    },
    {
      "id": 64920393,
      "code": "060104338",
      "nickname": "ぺんぎん",
      "level": 221,
      "score": 214182,
      "achievement": "期待のルーキー",
      "character_id": 14122,
      "rank": 13
    },
    {
      "id": 80974379,
      "code": "505330643",
      "nickname": "越後屋",
      "level": 131,
      "score": 213555,
      "achievement": "期待のルーキー",
      "character_id": 13702,
      "rank": 14
    },
    {
      "id": 69653010,
      "code": "668381275",
      "nickname": "Zzz",
      "level": 553,
      "score": 212785,
      "achievement": "<icon=common_font_pirate_rumble_grandparty_sp_0068_luffy_kaidou.png>と<icon=common_font_pirate_rumble_grandparty_0059_luffy_roger.png>",
      "character_id": 13903,
      "rank": 15
    },
    {
      "id": 76811826,
      "code": "818914131",
      "nickname": "むー",
      "level": 542,
      "score": 211845,
      "achievement": "ふしだらの聖地マリージョア",
      "character_id": 13472,
      "rank": 16
    },
    {
      "id": 44573245,
      "code": "736608863",
      "nickname": "まっとー",
      "level": 590,
      "score": 211585,
      "achievement": "<icon=common_font_pirate_rumble_grandparty_sp_0068_luffy_kaidou.png>そして<icon=common_font_kizuna_battle_0056_mugiwara_1.png>",
      "character_id": 13472,
      "rank": 17
    },
    {
      "id": 15017556,
      "code": "680126392",
      "nickname": "ＰＡＮＤＡＭＡＮ",
      "level": 771,
      "score": 211026,
      "achievement": "<icon=common_font_pirate_rumble_grandparty_0020_sirohige.png><icon=common_font_pirate_rumble_grandparty_0023_ace.png>",
      "character_id": 10153,
      "rank": 18
    },
    {
      "id": 79314276,
      "code": "373775181",
      "nickname": "腰痛たこ爺✰࿐⋆",
      "level": 642,
      "score": 210935,
      "achievement": "<icon=common_font_kizuna_battle_0080_kuma_1.png><icon=common_font_grandparty_0094_saturn_bonny_14452_14457.png>",
      "character_id": 13358,
      "rank": 19
    },
    {
      "id": 20557822,
      "code": "724251373",
      "nickname": "ピロシキン",
      "level": 292,
      "score": 210610,
      "achievement": "ヘビースモーカーな世界の歌姫",
      "character_id": 12760,
      "rank": 20
    },
    {
      "id": 27961980,
      "code": "475092135",
      "nickname": "べっちゃ！",
      "level": 649,
      "score": 210250,
      "achievement": "期待のルーキー",
      "character_id": 13414,
      "rank": 21
    },
    {
      "id": 61282066,
      "code": "548311143",
      "nickname": "♡あーにゃ卍",
      "level": 356,
      "score": 209965,
      "achievement": "<icon=common_font_pirate_rumble_grandparty_0059_luffy_roger.png><icon=common_font_grandparty_sp_0093_luffy_zoro_sanji_14251.png>",
      "character_id": 14517,
      "rank": 22
    },
    {
      "id": 63806691,
      "code": "999504835",
      "nickname": "\"もちもち海賊団\"",
      "level": 1095,
      "score": 209835,
      "achievement": "<icon=common_font_pirate_rumble_grandparty_0062_sanji.png>の黒足",
      "character_id": 12760,
      "rank": 23
    },
    {
      "id": 39898582,
      "code": "769507937",
      "nickname": "tamnos~",
      "level": 223,
      "score": 209305,
      "achievement": "三刀流なわらわ",
      "character_id": 13358,
      "rank": 24
    },
    {
      "id": 8892123,
      "code": "944133303",
      "nickname": "ponikoの仲間達",
      "level": 1230,
      "score": 209290,
      "achievement": "ギックリ腰き太郎",
      "character_id": 10153,
      "rank": 25
    },
    {
      "id": 15007144,
      "code": "629283329",
      "nickname": "༻мдтсн༺",
      "level": 1281,
      "score": 208690,
      "achievement": "<icon=common_font_kizuna_battle_0097_mihawk_perona_1_14511.png>の<icon=common_font_dairansen_ranking_mihawk.png>",
      "character_id": 12969,
      "rank": 26
    },
    {
      "id": 71028049,
      "code": "114187361",
      "nickname": "炙りサーモン",
      "level": 249,
      "score": 208275,
      "achievement": "期待のルーキー",
      "character_id": 13358,
      "rank": 27
    },
    {
      "id": 79110065,
      "code": "331780148",
      "nickname": "麦わらの一味",
      "level": 172,
      "score": 208206,
      "achievement": "期待のルーキー",
      "character_id": 13358,
      "rank": 28
    },
    {
      "id": 57715792,
      "code": "884187243",
      "nickname": "マーク",
      "level": 335,
      "score": 207950,
      "achievement": "",
      "character_id": 13632,
      "rank": 29
    },
    {
      "id": 63111125,
      "code": "811438893",
      "nickname": "ズンドコベロンチョ",
      "level": 358,
      "score": 207904,
      "achievement": "世界の歌姫をペロリン♪",
      "character_id": 13358,
      "rank": 30
    },
    {
      "id": 80432242,
      "code": "374528733",
      "nickname": "リル",
      "level": 179,
      "score": 207550,
      "achievement": "イカつい女帝",
      "character_id": 14523,
      "rank": 31
    },
    {
      "id": 29092261,
      "code": "603047377",
      "nickname": "マサわらの一味",
      "level": 725,
      "score": 207149,
      "achievement": "月影の冥王",
      "character_id": 12969,
      "rank": 32
    },
    {
      "id": 79781020,
      "code": "135114171",
      "nickname": "まある",
      "level": 376,
      "score": 206874,
      "achievement": "<icon=common_font_grandparty_0096_nami_yamato_otama_14301_14422.png><icon=common_font_grandparty_sp_0093_luffy_zoro_sanji_14251.png>",
      "character_id": 12760,
      "rank": 33
    },
    {
      "id": 6053066,
      "code": "161283643",
      "nickname": "黒髭海賊団",
      "level": 784,
      "score": 206872,
      "achievement": "ド派手なサービス",
      "character_id": 13472,
      "rank": 34
    },
    {
      "id": 81056721,
      "code": "161358203",
      "nickname": "麦わらの一味",
      "level": 36,
      "score": 206720,
      "achievement": "期待のルーキー",
      "character_id": 14436,
      "rank": 35
    },
    {
      "id": 14649975,
      "code": "926895873",
      "nickname": "ひまわり",
      "level": 565,
      "score": 206195,
      "achievement": "三刀流の女",
      "character_id": 12760,
      "rank": 36
    },
    {
      "id": 244717,
      "code": "463958537",
      "nickname": "あっきー",
      "level": 1197,
      "score": 206130,
      "achievement": "期待のルーキー",
      "character_id": 12760,
      "rank": 37
    },
    {
      "id": 75303073,
      "code": "795361312",
      "nickname": "くろくま",
      "level": 419,
      "score": 206107,
      "achievement": "<icon=common_font_pirate_rumble_grandparty_sp_0068_luffy_kaidou.png><icon=common_font_pirate_rumble_grandparty_0059_luffy_roger.png>",
      "character_id": 1536,
      "rank": 38
    },
    {
      "id": 39572696,
      "code": "655374314",
      "nickname": "BakaHentai",
      "level": 842,
      "score": 205845,
      "achievement": "期待のルーキー",
      "character_id": 14525,
      "rank": 39
    },
    {
      "id": 68614045,
      "code": "883881338",
      "nickname": "へのぬーん",
      "level": 1023,
      "score": 205617,
      "achievement": "雑用のおもろいおっさん",
      "character_id": 14122,
      "rank": 40
    },
    {
      "id": 33961553,
      "code": "653501309",
      "nickname": "伝説のおしり",
      "level": 943,
      "score": 205612,
      "achievement": "メロメロでやんす",
      "character_id": 12969,
      "rank": 41
    },
    {
      "id": 61071730,
      "code": "617685813",
      "nickname": "かこじ",
      "level": 674,
      "score": 205597,
      "achievement": "ハズレは許さねェ",
      "character_id": 12969,
      "rank": 42
    },
    {
      "id": 66820235,
      "code": "838187079",
      "nickname": "TN",
      "level": 860,
      "score": 205420,
      "achievement": "<icon=common_font_dairansen_0090_kizaru_nyusyo_14411.png><icon=common_font_super_pirate_rumble_0086_osoba_mask_nyusyo.png>",
      "character_id": 13472,
      "rank": 43
    },
    {
      "id": 74373845,
      "code": "366748816",
      "nickname": "ばびぶぅ",
      "level": 477,
      "score": 205342,
      "achievement": "",
      "character_id": 13472,
      "rank": 44
    },
    {
      "id": 80903517,
      "code": "639636950",
      "nickname": "吉田沙保里",
      "level": 228,
      "score": 205275,
      "achievement": "期待のルーキー",
      "character_id": 13602,
      "rank": 45
    },
    {
      "id": 80253767,
      "code": "552938363",
      "nickname": "みわｺｯｸ",
      "level": 189,
      "score": 205202,
      "achievement": "ゴロゴロの女帝",
      "character_id": 13358,
      "rank": 46
    },
    {
      "id": 65848360,
      "code": "927530378",
      "nickname": "麦わら大船団",
      "level": 729,
      "score": 205013,
      "achievement": "クルッポーな覇王色の覚醒者",
      "character_id": 13472,
      "rank": 47
    },
    {
      "id": 32420330,
      "code": "200731550",
      "nickname": "つっちゃん",
      "level": 467,
      "score": 204810,
      "achievement": "<icon=common_font_10th.png><icon=common_font_pirate_rumble_grandparty_0059_luffy_roger.png>",
      "character_id": 14251,
      "rank": 48
    },
    {
      "id": 39439493,
      "code": "394293573",
      "nickname": "LIFE",
      "level": 638,
      "score": 204787,
      "achievement": "<icon=common_font_grandparty_0098_garling_garp_14512_14513.png>の<icon=common_font_pirate_rumble_grandparty_0073_shanks_kid.png>",
      "character_id": 13472,
      "rank": 49
    },
    {
      "id": 62901415,
      "code": "009869318",
      "nickname": "粋な魚屋さん",
      "level": 508,
      "score": 204780,
      "achievement": "力自慢の武闘派",
      "character_id": 13472,
      "rank": 50
    },
    {
      "id": 3548989,
      "code": "439237794",
      "nickname": "関水渚推ノ助↑",
      "level": 634,
      "score": 204692,
      "achievement": "よい",
      "character_id": 12969,
      "rank": 51
    },
    {
      "id": 77068096,
      "code": "111547364",
      "nickname": "e",
      "level": 158,
      "score": 204675,
      "achievement": "期待のルーキー",
      "character_id": 13701,
      "rank": 52
    },
    {
      "id": 73250305,
      "code": "501290823",
      "nickname": "しょうごの一味",
      "level": 675,
      "score": 204452,
      "achievement": "<icon=common_font_11th_0091.png>の司令官",
      "character_id": 12575,
      "rank": 53
    },
    {
      "id": 55573087,
      "code": "962169332",
      "nickname": "ぽんたっった",
      "level": 641,
      "score": 204277,
      "achievement": "期待のルーキー",
      "character_id": 13472,
      "rank": 54
    },
    {
      "id": 67550264,
      "code": "782230334",
      "nickname": "サムライ",
      "level": 927,
      "score": 204272,
      "achievement": "<icon=common_font_grandparty_0098_garling_garp_14512_14513.png><icon=common_font_pirate_rumble_grandparty_0088_pica_dfla_14359_14351.png>",
      "character_id": 13465,
      "rank": 55
    },
    {
      "id": 19705137,
      "code": "397193987",
      "nickname": "下衆の極み一味　",
      "level": 678,
      "score": 203730,
      "achievement": "期待のルーキー",
      "character_id": 10153,
      "rank": 56
    },
    {
      "id": 68358724,
      "code": "223871738",
      "nickname": "seiji海賊団。",
      "level": 445,
      "score": 203030,
      "achievement": "<icon=common_font_super_pirate_rumble_0050_kaido_nyusyo.png>",
      "character_id": 13361,
      "rank": 57
    },
    {
      "id": 18874615,
      "code": "693586933",
      "nickname": "山田仮太郎",
      "level": 721,
      "score": 202957,
      "achievement": "ヘッポコな称号はもういらねェ",
      "character_id": 13358,
      "rank": 58
    },
    {
      "id": 43270148,
      "code": "896030536",
      "nickname": "りくちゃん海賊団",
      "level": 357,
      "score": 202656,
      "achievement": "聖地マリージョアの最強の生物",
      "character_id": 13358,
      "rank": 59
    },
    {
      "id": 77033836,
      "code": "371416463",
      "nickname": "がりがりくん",
      "level": 327,
      "score": 202525,
      "achievement": "期待のルーキー",
      "character_id": 14513,
      "rank": 60
    },
    {
      "id": 59929924,
      "code": "222139017",
      "nickname": "灰犬海賊団",
      "level": 701,
      "score": 202077,
      "achievement": "犬のチョニキ",
      "character_id": 13472,
      "rank": 61
    },
    {
      "id": 6353164,
      "code": "234783326",
      "nickname": "ᔕᗩᗩƙ︎✿",
      "level": 1570,
      "score": 201937,
      "achievement": "腐れ小豆",
      "character_id": 13701,
      "rank": 62
    },
    {
      "id": 11458176,
      "code": "521373921",
      "nickname": "王下七武海",
      "level": 469,
      "score": 201892,
      "achievement": "期待のルーキー",
      "character_id": 13472,
      "rank": 63
    },
    {
      "id": 45226798,
      "code": "658124503",
      "nickname": "海鷂魚.",
      "level": 392,
      "score": 201685,
      "achievement": "期待のルーキー",
      "character_id": 11104,
      "rank": 64
    },
    {
      "id": 28239602,
      "code": "533725397",
      "nickname": "未来の海賊王",
      "level": 763,
      "score": 201345,
      "achievement": "<icon=common_font_pirate_rumble_grandparty_0070_kurohige_law.png>と<icon=common_font_pirate_rumble_grandparty_sp_0081_luffy_sabo_ace.png>",
      "character_id": 12969,
      "rank": 65
    },
    {
      "id": 21931651,
      "code": "303751001",
      "nickname": "四皇のそらっち",
      "level": 1016,
      "score": 201262,
      "achievement": "<icon=common_font_world_cruise2024_0053_nami_kantou.png>の<icon=common_font_10th.png>",
      "character_id": 14203,
      "rank": 66
    },
    {
      "id": 70862568,
      "code": "364593651",
      "nickname": "麦わらの一味",
      "level": 632,
      "score": 201100,
      "achievement": "期待のルーキー",
      "character_id": 14517,
      "rank": 67
    },
    {
      "id": 34942912,
      "code": "667524037",
      "nickname": "麦わらの一味！",
      "level": 655,
      "score": 201055,
      "achievement": "期待のルーキー",
      "character_id": 10153,
      "rank": 68
    },
    {
      "id": 66108953,
      "code": "489302378",
      "nickname": "麦麦",
      "level": 353,
      "score": 200972,
      "achievement": "<icon=common_font_pirate_rumble_grandparty_0059_luffy_roger.png>",
      "character_id": 14251,
      "rank": 69
    },
    {
      "id": 38435214,
      "code": "823357263",
      "nickname": "。。。",
      "level": 401,
      "score": 200809,
      "achievement": "自由を忘れるな！",
      "character_id": 14511,
      "rank": 70
    },
    {
      "id": 9181588,
      "code": "474696314",
      "nickname": "MMR",
      "level": 814,
      "score": 200754,
      "achievement": "エロゴリラ",
      "character_id": 10153,
      "rank": 71
    },
    {
      "id": 61381123,
      "code": "411133873",
      "nickname": "大大大猿神群鴉砲",
      "level": 616,
      "score": 200610,
      "achievement": "麗しき世界の歌姫",
      "character_id": 10153,
      "rank": 72
    },
    {
      "id": 52134904,
      "code": "202332342",
      "nickname": "うどんには絶対一味",
      "level": 327,
      "score": 200465,
      "achievement": "<icon=common_font_grandparty_0098_garling_garp_14512_14513.png>そして<icon=common_font_grandparty_0096_nami_yamato_otama_14301_14422.png>",
      "character_id": 12760,
      "rank": 73
    },
    {
      "id": 46720990,
      "code": "035421180",
      "nickname": "ユニコーン海賊団",
      "level": 259,
      "score": 200350,
      "achievement": "<icon=common_font_pirate_rumble_grandparty_sp_0068_luffy_kaidou.png><icon=common_font_pirate_rumble_grandparty_0059_luffy_roger.png>",
      "character_id": 14251,
      "rank": 74
    },
    {
      "id": 45824878,
      "code": "592334016",
      "nickname": "M・G・A",
      "level": 668,
      "score": 200267,
      "achievement": "期待のルーキー",
      "character_id": 14370,
      "rank": 75
    },
    {
      "id": 67710211,
      "code": "186007384",
      "nickname": "やさし",
      "level": 441,
      "score": 200135,
      "achievement": "<icon=common_font_grandparty_0092_kuma_pegapunk_14401_14402.png>の壁",
      "character_id": 13472,
      "rank": 76
    },
    {
      "id": 13438691,
      "code": "357924039",
      "nickname": "t.s",
      "level": 1077,
      "score": 199977,
      "achievement": "4人目の一家",
      "character_id": 12760,
      "rank": 77
    },
    {
      "id": 42518263,
      "code": "377803303",
      "nickname": "たいのすけ",
      "level": 857,
      "score": 199802,
      "achievement": "やんすやんす",
      "character_id": 14122,
      "rank": 78
    },
    {
      "id": 61549222,
      "code": "918337717",
      "nickname": "ojun1",
      "level": 303,
      "score": 199655,
      "achievement": "最悪の<icon=common_font_super_pirate_rumble_akainu_kantou.png>",
      "character_id": 13554,
      "rank": 79
    },
    {
      "id": 62532287,
      "code": "498337309",
      "nickname": "よもぎ☺︎",
      "level": 834,
      "score": 199374,
      "achievement": "期待のルーキー",
      "character_id": 13472,
      "rank": 80
    },
    {
      "id": 80531975,
      "code": "535312338",
      "nickname": "おが",
      "level": 318,
      "score": 199209,
      "achievement": "バスターコールはゴールデン",
      "character_id": 11924,
      "rank": 81
    },
    {
      "id": 6400304,
      "code": "204280293",
      "nickname": "黒服 フレ募集",
      "level": 1012,
      "score": 198725,
      "achievement": "期待のルーキー",
      "character_id": 14552,
      "rank": 82
    },
    {
      "id": 81040088,
      "code": "137691036",
      "nickname": "JuuN",
      "level": 221,
      "score": 198635,
      "achievement": "期待のルーキー",
      "character_id": 13358,
      "rank": 83
    },
    {
      "id": 72518446,
      "code": "801197338",
      "nickname": "star",
      "level": 281,
      "score": 198211,
      "achievement": "神の天敵がアーマードおれ",
      "character_id": 13358,
      "rank": 84
    },
    {
      "id": 58884025,
      "code": "831431923",
      "nickname": "りくとの一味",
      "level": 290,
      "score": 198172,
      "achievement": "<icon=common_font_kizuna_battle_0039_yamato_1.png>と<icon=common_font_kizuna_battle_roger_1.png>",
      "character_id": 14463,
      "rank": 85
    },
    {
      "id": 35339486,
      "code": "179939325",
      "nickname": "Ꮹｏ",
      "level": 1143,
      "score": 198156,
      "achievement": "ニャニャ",
      "character_id": 12760,
      "rank": 86
    },
    {
      "id": 50817339,
      "code": "754202938",
      "nickname": "麦わらの一味",
      "level": 580,
      "score": 198067,
      "achievement": "期待のルーキー",
      "character_id": 1536,
      "rank": 87
    },
    {
      "id": 12640549,
      "code": "708864903",
      "nickname": "∮ᎦᎻᏫ∮☁️⋆͛",
      "level": 1021,
      "score": 198052,
      "achievement": "<icon=common_font_gekitou_lufy_sanji_2.png>",
      "character_id": 14122,
      "rank": 88
    },
    {
      "id": 71265400,
      "code": "855319521",
      "nickname": "Nokuto",
      "level": 592,
      "score": 198020,
      "achievement": "<icon=common_font_pirate_rumble_grandparty_0074_roger_reilly_gabin.png><icon=common_font_kizuna_battle_0065_moria_1.png>",
      "character_id": 13472,
      "rank": 89
    },
    {
      "id": 7047923,
      "code": "243712364",
      "nickname": "tomo",
      "level": 497,
      "score": 197980,
      "achievement": "<icon=common_font_10th.png><icon=common_font_pirate_rumble_grandparty_0059_luffy_roger.png>",
      "character_id": 12760,
      "rank": 90
    },
    {
      "id": 9576347,
      "code": "658309473",
      "nickname": "Red✳︎bean",
      "level": 951,
      "score": 197977,
      "achievement": "スケスケだよーん",
      "character_id": 14552,
      "rank": 91
    },
    {
      "id": 50583508,
      "code": "342666325",
      "nickname": "麦わらの一味",
      "level": 606,
      "score": 197947,
      "achievement": "雑用の海賊王",
      "character_id": 14251,
      "rank": 92
    },
    {
      "id": 77551369,
      "code": "143120334",
      "nickname": "ロー",
      "level": 813,
      "score": 197925,
      "achievement": "死の外科医",
      "character_id": 14551,
      "rank": 93
    },
    {
      "id": 73874010,
      "code": "153193966",
      "nickname": "PREDATOR",
      "level": 649,
      "score": 197865,
      "achievement": "<icon=common_font_grandparty_0094_saturn_bonny_14452_14457.png>と<icon=common_font_grandparty_0098_garling_garp_14512_14513.png>",
      "character_id": 14525,
      "rank": 94
    },
    {
      "id": 64758090,
      "code": "124571386",
      "nickname": "麦わら海賊団",
      "level": 250,
      "score": 197810,
      "achievement": "期待のルーキー",
      "character_id": 13358,
      "rank": 95
    },
    {
      "id": 78116066,
      "code": "343151813",
      "nickname": "なおぽんぜよ",
      "level": 433,
      "score": 197790,
      "achievement": "ごめんね男じゃないよ！！？",
      "character_id": 14006,
      "rank": 96
    },
    {
      "id": 50173934,
      "code": "467262325",
      "nickname": "༺解放の戦士༻タケシ",
      "level": 676,
      "score": 197563,
      "achievement": "<icon=common_font_pirate_rumble_grandparty_0035_luffy_gear5.png><icon=common_font_grandparty_0094_saturn_bonny_14452_14457.png>",
      "character_id": 13704,
      "rank": 97
    },
    {
      "id": 8250034,
      "code": "214230573",
      "nickname": "おぎお一味",
      "level": 534,
      "score": 197485,
      "achievement": "期待のルーキー",
      "character_id": 13472,
      "rank": 98
    },
    {
      "id": 2979879,
      "code": "354049406",
      "nickname": "-Rufus-",
      "level": 763,
      "score": 197392,
      "achievement": "期待のルーキー",
      "character_id": 10153,
      "rank": 99
    },
    {
      "id": 50564818,
      "code": "356634325",
      "nickname": "☆S.K☆",
      "level": 416,
      "score": 197180,
      "achievement": "<icon=common_font_grandparty_0094_saturn_bonny_14452_14457.png>",
      "character_id": 13358,
      "rank": 100
    }
  ],
  "rank_border_scores": [
    {
      "rank_id": 1,
      "score": 139515
    },
    {
      "rank_id": 2,
      "score": 115025
    },
    {
      "rank_id": 3,
      "score": 94010
    },
    {
      "rank_id": 4,
      "score": 70275
    },
    {
      "rank_id": 5,
      "score": 49819
    },
    {
      "rank_id": 6,
      "score": 25075
    },
    {
      "rank_id": 7,
      "score": 200
    }
  ]
}